fancySVD
