Metadata-Version: 2.1
Name: fancySVD
Version: 0.1.2
Summary: Matrix completion and feature imputation algorithms
Home-page: https://github.com/AlexsLemonade/fancySVD
Author: Alex Rubinsteyn, Sergey Feldman, Kurt Wheeler
Author-email: kurt@ccdatalab.org
License: http://www.apache.org/licenses/LICENSE-2.0.html
Platform: UNKNOWN
Classifier: Development Status :: 4 - Beta
Classifier: Environment :: Console
Classifier: Operating System :: OS Independent
Classifier: Intended Audience :: Science/Research
Classifier: License :: OSI Approved :: Apache Software License
Classifier: Programming Language :: Python
Classifier: Topic :: Scientific/Engineering :: Bio-Informatics
License-File: LICENSE
